tests/__init__.py
tests/test_examples.py
tests/test_slicemap.py
tests/test_text_normalization.py
tests/test_whisper_asr.py
transcription_diff/__init__.py
transcription_diff/find_lang_match.py
transcription_diff/number_normalization.py
transcription_diff/slice_map.py
transcription_diff/text_diff.py
transcription_diff/text_normalization.py
transcription_diff/whisper_asr.py
transcription_diff-0.1.3.dist-info/LICENSE
transcription_diff-0.1.3.dist-info/METADATA
transcription_diff-0.1.3.dist-info/WHEEL
transcription_diff-0.1.3.dist-info/top_level.txt
transcription_diff-0.1.3.dist-info/RECORD
